systemy/__init__.py
systemy/loaders.py
systemy/system.py
systemy-0.1.5.dist-info/WHEEL
systemy-0.1.5.dist-info/METADATA
systemy-0.1.5.dist-info/RECORD
