Metadata-Version: 2.1
Name: systemy
Version: 0.1.5
Summary: A core package to manipulate model or system hierarchical classes
Author: Sylvain Guieu
Author-email: sylvain.guieu@gmail.com
Requires-Python: >=3.7,<4.0
Classifier: Programming Language :: Python :: 3
Classifier: Programming Language :: Python :: 3.7
Classifier: Programming Language :: Python :: 3.8
Classifier: Programming Language :: Python :: 3.9
Classifier: Programming Language :: Python :: 3.10
Classifier: Programming Language :: Python :: 3.11
Requires-Dist: attrs (>=22.2.0,<23.0.0)
Requires-Dist: py-expression-eval (>=0.3.14,<0.4.0)
Requires-Dist: pydantic (>=1.9.0,<2.0.0)
Requires-Dist: pyyaml (>=6.0,<7.0)
